benchmarks/fvd/__init__.py
benchmarks/fvd/cli.py
benchmarks/fvd/feature_extractors.py
benchmarks/fvd/fvd.py
benchmarks/fvd/i3d_model.py
benchmarks/fvd/run_fvd.py
benchmarks/fvd/validate_fvd.py
benchmarks/fvd/video_utils.py
comfyui/__init__.py
comfyui/video_generator/dit_config.py
comfyui/video_generator/inference_args.py
comfyui/video_generator/load_image.py
comfyui/video_generator/node_helpers.py
comfyui/video_generator/nodes.py
comfyui/video_generator/text_encoder_config.py
comfyui/video_generator/vae_config.py
comfyui/video_generator/video_generator.py
demo/gradio_web_demo.py
examples/inference/basic/basic.py
examples/inference/basic/basic_dmd.py
examples/inference/basic/basic_hy15.py
examples/inference/basic/basic_matrixgame.py
examples/inference/basic/basic_matrixgame_streaming.py
examples/inference/basic/basic_mps.py
examples/inference/basic/basic_ray.py
examples/inference/basic/basic_self_forcing_causal.py
examples/inference/basic/basic_self_forcing_causal_wan2_2_i2v.py
examples/inference/basic/basic_self_forcing_causal_wan2_2_t2v.py
examples/inference/basic/basic_turbodiffusion.py
examples/inference/basic/basic_turbodiffusion_14b.py
examples/inference/basic/basic_turbodiffusion_i2v.py
examples/inference/basic/basic_wan2_2.py
examples/inference/basic/basic_wan2_2_Fun.py
examples/inference/basic/basic_wan2_2_i2v.py
examples/inference/basic/basic_wan2_2_ti2v.py
examples/inference/gradio/local/gradio_local_demo.py
examples/inference/gradio/local/gradio_local_demo_matrixgame.py
examples/inference/gradio/serving/gradio_frontend.py
examples/inference/gradio/serving/ray_serve_backend.py
examples/inference/gradio/serving/start_ray_serve_app.py
examples/inference/lora/wan_lora_inference.py
examples/inference/lora/wan_lora_inference_from_ckpt.py
examples/inference/optimizations/attention_example.py
examples/inference/optimizations/teacache_example.py
examples/inference/optimizations/text_encoder_quant_example.py
examples/inference/sta_mask_search/wan_example.py
fastvideo-0.1.7.dist-info/licenses/LICENSE
fastvideo-0.1.7.dist-info/METADATA
fastvideo-0.1.7.dist-info/WHEEL
fastvideo-0.1.7.dist-info/entry_points.txt
fastvideo-0.1.7.dist-info/top_level.txt
fastvideo-0.1.7.dist-info/RECORD
