Metadata-Version: 2.4
Name: fastvideo
Version: 0.1.7
Summary: FastVideo
Project-URL: Repository, https://github.com/hao-ai-lab/FastVideo
Classifier: Programming Language :: Python :: 3
Classifier: License :: OSI Approved :: Apache Software License
Requires-Python: >=3.10
License-File: LICENSE
Requires-Dist: scipy==1.14.1
Requires-Dist: six==1.16.0
Requires-Dist: h5py==3.12.1
Requires-Dist: requests>=2.32.2
Requires-Dist: transformers==4.57.3
Requires-Dist: tokenizers>=0.20.1
Requires-Dist: sentencepiece==0.2.0
Requires-Dist: timm==1.0.11
Requires-Dist: peft>=0.15.0
Requires-Dist: diffusers>=0.33.1
Requires-Dist: torch>=2.9.1
Requires-Dist: torchvision
Requires-Dist: accelerate==1.0.1
Requires-Dist: opencv-python==4.10.0.84
Requires-Dist: pillow>=10.3.0
Requires-Dist: imageio==2.36.0
Requires-Dist: imageio-ffmpeg==0.5.1
Requires-Dist: einops
Requires-Dist: wandb>=0.21.0
Requires-Dist: loguru
Requires-Dist: test-tube==0.7.5
Requires-Dist: tqdm
Requires-Dist: pytest
Requires-Dist: PyYAML==6.0.1
Requires-Dist: protobuf>=5.28.3
Requires-Dist: gradio==5.32.0
Requires-Dist: moviepy>=2.0.0
Requires-Dist: flask
Requires-Dist: flask_restful
Requires-Dist: aiohttp
Requires-Dist: huggingface_hub
Requires-Dist: cloudpickle
Requires-Dist: gpustat
Requires-Dist: watch
Requires-Dist: remote-pdb
Requires-Dist: fastvideo-kernel==0.2.2
Requires-Dist: wheel
Requires-Dist: torchdata
Requires-Dist: pyarrow
Requires-Dist: datasets==4.0.0
Requires-Dist: av
Requires-Dist: torchcodec==0.5.0
Requires-Dist: ray>=2.49.1
Requires-Dist: ftfy==6.3.1
Provides-Extra: lint
Requires-Dist: pre-commit==4.0.1; extra == "lint"
Provides-Extra: test
Requires-Dist: av==14.3.0; extra == "test"
Requires-Dist: pytorch-msssim==1.0.0; extra == "test"
Requires-Dist: pytest; extra == "test"
Provides-Extra: dev
Requires-Dist: fastvideo[lint]; extra == "dev"
Requires-Dist: fastvideo[test]; extra == "dev"
Provides-Extra: rocm
Requires-Dist: amdsmi; extra == "rocm"
Dynamic: license-file
